odoo/addons/fieldservice_sale/README.rst
odoo/addons/fieldservice_sale/__init__.py
odoo/addons/fieldservice_sale/__manifest__.py
odoo/addons/fieldservice_sale/models/__init__.py
odoo/addons/fieldservice_sale/models/fsm_location.py
odoo/addons/fieldservice_sale/models/fsm_order.py
odoo/addons/fieldservice_sale/models/fsm_recurring.py
odoo/addons/fieldservice_sale/models/product.py
odoo/addons/fieldservice_sale/models/sale_order.py
odoo/addons/fieldservice_sale/readme/CONFIGURE.rst
odoo/addons/fieldservice_sale/readme/CONTRIBUTORS.rst
odoo/addons/fieldservice_sale/readme/CREDITS.rst
odoo/addons/fieldservice_sale/readme/DESCRIPTION.rst
odoo/addons/fieldservice_sale/readme/INSTALL.rst
odoo/addons/fieldservice_sale/readme/ROADMAP.rst
odoo/addons/fieldservice_sale/readme/USAGE.rst
odoo/addons/fieldservice_sale/static/description/icon.png
odoo/addons/fieldservice_sale/static/description/index.html
odoo/addons/fieldservice_sale/static/description/description/icon.png
odoo/addons/fieldservice_sale/static/description/description/index.html
odoo/addons/fieldservice_sale/views/fsm_location.xml
odoo/addons/fieldservice_sale/views/fsm_order.xml
odoo/addons/fieldservice_sale/views/fsm_recurring.xml
odoo/addons/fieldservice_sale/views/product.xml
odoo/addons/fieldservice_sale/views/sale_order.xml
odoo11_addon_fieldservice_sale-11.0.0.1.0.99.dev5.dist-info/METADATA
odoo11_addon_fieldservice_sale-11.0.0.1.0.99.dev5.dist-info/WHEEL
odoo11_addon_fieldservice_sale-11.0.0.1.0.99.dev5.dist-info/top_level.txt
odoo11_addon_fieldservice_sale-11.0.0.1.0.99.dev5.dist-info/RECORD
